<OutOfBrowserSettings ShortName="文档管理系统" EnableGPUAcceleration="False" ShowInstallMenuItem="True">
  <OutOfBrowserSettings.Blurb>文档管理系统</OutOfBrowserSettings.Blurb>
  <OutOfBrowserSettings.WindowSettings>
    <WindowSettings Title="文档管理系统" WindowStyle="None" />
  </OutOfBrowserSettings.WindowSettings>
  <OutOfBrowserSettings.SecuritySettings>
    <SecuritySettings ElevatedPermissions="Required" />
  </OutOfBrowserSettings.SecuritySettings>
  <OutOfBrowserSettings.Icons />
</OutOfBrowserSettings>